<root>
  <entities>
    <entity>
      <id>5</id>
      <type>SpawnPoint</type>
      <monsterSpawntPoint>18260,13294,18381,12765,18017,13051,18445,12382,18738,12477,18413,13025,17755,13006,18686,13062,18089,12325,17867,13296,18983,12770,18025,13494,17793,12426,18705,12762,17888,12774</monsterSpawntPoint>
      <triggerType>0</triggerType>
      <preSpawnPointId>
      </preSpawnPointId>
      <levelID>107025, 207025</levelID>
      <triggeRangeX>17538</triggeRangeX>
      <triggeRangeY>13365</triggeRangeY>
      <triggeRangeLength>659</triggeRangeLength>
      <triggeRangeWidth>2039</triggeRangeWidth>
      <homerangeX>18496</homerangeX>
      <homerangeY>12973</homerangeY>
      <homerangeLength>3540</homerangeLength>
      <homerangeWidth>3729</homerangeWidth>
    </entity>
    <entity>
      <id>4</id>
      <type>SpawnPoint</type>
      <monsterSpawntPoint>15820,14235,15938,14446,16267,13597,16033,14747,16387,13813,16253,14245,15923,13633,16266,14432,16054,13844,16221,14038,15725,13933,16584,13656,16565,13430,16069,15004,16038,14162</monsterSpawntPoint>
      <triggerType>0</triggerType>
      <preSpawnPointId>
      </preSpawnPointId>
      <levelID>107024, 207024</levelID>
      <triggeRangeX>0</triggeRangeX>
      <triggeRangeY>0</triggeRangeY>
      <triggeRangeLength>0</triggeRangeLength>
      <triggeRangeWidth>0</triggeRangeWidth>
      <homerangeX>16181</homerangeX>
      <homerangeY>14009</homerangeY>
      <homerangeLength>2939</homerangeLength>
      <homerangeWidth>3000</homerangeWidth>
    </entity>
    <entity>
      <id>2</id>
      <type>SpawnPoint</type>
      <monsterSpawntPoint>11507,16878,11686,16356,12156,16330,11767,16024,12187,16568,12170,16850,11937,16633,12018,17208,11726,17133,11856,16231,11386,16360,11572,16590,11819,16890</monsterSpawntPoint>
      <triggerType>0</triggerType>
      <preSpawnPointId>
      </preSpawnPointId>
      <levelID>107022, 207022</levelID>
      <triggeRangeX>0</triggeRangeX>
      <triggeRangeY>0</triggeRangeY>
      <triggeRangeLength>0</triggeRangeLength>
      <triggeRangeWidth>0</triggeRangeWidth>
      <homerangeX>11923</homerangeX>
      <homerangeY>16005</homerangeY>
      <homerangeLength>9659</homerangeLength>
      <homerangeWidth>7290</homerangeWidth>
    </entity>
    <entity>
      <id>3</id>
      <type>SpawnPoint</type>
      <monsterSpawntPoint>15113,16601,15061,16959,16259,16503,15960,16391,15665,16346,15956,16970,16066,15996,15407,17101,14639,16983,15445,16560,15734,17205,15807,16679,16239,16234,16138,16773,15544,16830</monsterSpawntPoint>
      <triggerType>0</triggerType>
      <preSpawnPointId>
      </preSpawnPointId>
      <levelID>107023, 207023</levelID>
      <triggeRangeX>0</triggeRangeX>
      <triggeRangeY>0</triggeRangeY>
      <triggeRangeLength>0</triggeRangeLength>
      <triggeRangeWidth>0</triggeRangeWidth>
      <homerangeX>15430</homerangeX>
      <homerangeY>16353</homerangeY>
      <homerangeLength>3139</homerangeLength>
      <homerangeWidth>3220</homerangeWidth>
    </entity>
    <entity>
      <id>99</id>
      <type>SpawnPoint</type>
      <monsterSpawntPoint>18202,12686</monsterSpawntPoint>
      <triggerType>0</triggerType>
      <preSpawnPointId>
      </preSpawnPointId>
      <levelID>107020, 207020</levelID>
      <triggeRangeX>17538</triggeRangeX>
      <triggeRangeY>13365</triggeRangeY>
      <triggeRangeLength>659</triggeRangeLength>
      <triggeRangeWidth>2039</triggeRangeWidth>
      <homerangeX>18272</homerangeX>
      <homerangeY>13047</homerangeY>
      <homerangeLength>3329</homerangeLength>
      <homerangeWidth>3690</homerangeWidth>
    </entity>
    <entity>
      <id>1</id>
      <type>SpawnPoint</type>
      <monsterSpawntPoint>11623,14800,10641,14824,9012,14937,11784,14608,9770,14991,11395,14967,11295,14572,11076,14766,10354,14959,11536,14407,9226,15089,10044,14910,8751,14819</monsterSpawntPoint>
      <triggerType>1</triggerType>
      <preSpawnPointId>
      </preSpawnPointId>
      <levelID>107021, 207021</levelID>
      <triggeRangeX>0</triggeRangeX>
      <triggeRangeY>0</triggeRangeY>
      <triggeRangeLength>0</triggeRangeLength>
      <triggeRangeWidth>0</triggeRangeWidth>
      <homerangeX>10661</homerangeX>
      <homerangeY>15829</homerangeY>
      <homerangeLength>7473</homerangeLength>
      <homerangeWidth>5740</homerangeWidth>
    </entity>
  </entities>
  <mapname>10702_s</mapname>
</root>